{
  "generated_at": "2026-07-10T05:00:41Z",
  "slate_date": "2026-07-09",
  "slate_timezone": "America/Los_Angeles",
  "schema_version": "3.3",
  "sources": {
    "league_news": "https://www.mlb.com/feeds/news/rss.xml",
    "athletics_news": "https://www.mlb.com/athletics/feeds/news/rss.xml",
    "tigers_news": "https://www.mlb.com/tigers/feeds/news/rss.xml",
    "rockies_news": "https://www.mlb.com/rockies/feeds/news/rss.xml",
    "league_standings": "https://statsapi.mlb.com/api/v1/standings?leagueId=103,104&season=2026",
    "league_schedule": "https://statsapi.mlb.com/api/v1/schedule?sportId=1&date=2026-07-09&hydrate=probablePitcher,team",
    "league_transactions": "https://statsapi.mlb.com/api/v1/transactions?startDate=2026-07-02&endDate=2026-07-09",
    "athletics_schedule": "https://statsapi.mlb.com/api/v1/schedule?sportId=1&teamId=133&startDate=2026-07-09&endDate=2026-07-11&hydrate=probablePitcher,team",
    "athletics_transactions": "https://statsapi.mlb.com/api/v1/transactions?teamId=133&startDate=2026-07-02&endDate=2026-07-09",
    "rockies_schedule": "https://statsapi.mlb.com/api/v1/schedule?sportId=1&teamId=115&startDate=2026-07-09&endDate=2026-07-11&hydrate=probablePitcher,team",
    "rockies_transactions": "https://statsapi.mlb.com/api/v1/transactions?teamId=115&startDate=2026-07-02&endDate=2026-07-09",
    "tigers_schedule": "https://statsapi.mlb.com/api/v1/schedule?sportId=1&teamId=116&startDate=2026-07-09&endDate=2026-07-11&hydrate=probablePitcher,team",
    "tigers_transactions": "https://statsapi.mlb.com/api/v1/transactions?teamId=116&startDate=2026-07-02&endDate=2026-07-09"
  },
  "source_status": {
    "league_standings": "verified",
    "league_schedule": "verified",
    "league_transactions": "verified",
    "athletics_standings": "verified",
    "athletics_schedule": "verified",
    "athletics_transactions": "verified",
    "rockies_standings": "verified",
    "rockies_schedule": "verified",
    "rockies_transactions": "verified",
    "tigers_standings": "verified",
    "tigers_schedule": "verified",
    "tigers_transactions": "verified",
    "league_news": "verified",
    "athletics_news": "verified",
    "tigers_news": "verified",
    "rockies_news": "verified",
    "curated_news_mlb_com": "verified",
    "curated_news_espn": "unverified",
    "curated_news_yahoo_sports": "verified",
    "bd_bets": "unverified"
  },
  "news": {
    "league_news": {
      "items": [
        {
          "headline": "Bauers pulls something out of 'The Matrix' to kickstart Brewers' rally",
          "url": "https://www.mlb.com/news/jake-bauers-pulls-off-impressive-dive-to-avoid-tag",
          "source": "MLB.com",
          "source_type": "rss",
          "published_at": "2026-07-10T04:36:00Z",
          "summary": ""
        },
        {
          "headline": "Valencia makes dream debut, becomes 10th Tiger to homer in first MLB at-bat",
          "url": "https://www.mlb.com/news/eduardo-valencia-homers-in-first-mlb-at-bat",
          "source": "MLB.com",
          "source_type": "rss",
          "published_at": "2026-07-10T03:25:00Z",
          "summary": ""
        },
        {
          "headline": "12 starting pitchers who could be on the move before the Trade Deadline",
          "url": "https://www.mlb.com/news/starting-pitcher-trade-rumors-2026-trade-deadline",
          "source": "MLB.com",
          "source_type": "rss",
          "published_at": "2026-07-10T04:00:18Z",
          "summary": ""
        },
        {
          "headline": "Langford's early return saves Rangers with walk-off winner",
          "url": "https://www.mlb.com/news/wyatt-langford-activated-off-injured-list-after-left-hamstring-strain",
          "source": "MLB.com",
          "source_type": "rss",
          "published_at": "2026-07-10T04:39:00Z",
          "summary": ""
        },
        {
          "headline": "6 Draft storylines to follow this weekend",
          "url": "https://www.mlb.com/news/6-mlb-draft-storylines-to-follow-2026",
          "source": "MLB.com",
          "source_type": "rss",
          "published_at": "2026-07-10T00:04:00Z",
          "summary": ""
        },
        {
          "headline": "Trade rumors: Braves, Mason Miller, Rays-Yanks bidding war?",
          "url": "https://www.mlb.com/news/mlb-trade-rumors-and-2026-trade-deadline-news-july-9",
          "source": "MLB.com",
          "source_type": "rss",
          "published_at": "2026-07-09T19:07:00Z",
          "summary": ""
        },
        {
          "headline": "The 'first All-Star Game' had long throw contests and actors lassoing players",
          "url": "https://www.mlb.com/news/1917-all-star-game-longest-throw-fungo-contest",
          "source": "MLB.com",
          "source_type": "rss",
          "published_at": "2026-07-10T04:00:15Z",
          "summary": ""
        },
        {
          "headline": "Luzardo struts stuff as newly minted All-Star with 7 scoreless in Cincy",
          "url": "https://www.mlb.com/news/jesus-luzardo-tosses-7-scoreless-innings-in-win-after-named-2026-all-star",
          "source": "MLB.com",
          "source_type": "rss",
          "published_at": "2026-07-10T02:53:00Z",
          "summary": ""
        },
        {
          "headline": "Junk leads Marlins to 10 games over .500 in 1st start back from IL",
          "url": "https://www.mlb.com/news/janson-junk-reinstated-from-injured-list",
          "source": "MLB.com",
          "source_type": "rss",
          "published_at": "2026-07-10T04:24:00Z",
          "summary": ""
        },
        {
          "headline": "Red Sox win 6th straight behind Patrick Sandoval's first start since 2024",
          "url": "https://www.mlb.com/news/patrick-sandoval-shines-in-red-sox-debut",
          "source": "MLB.com",
          "source_type": "rss",
          "published_at": "2026-07-09T23:03:00Z",
          "summary": ""
        }
      ],
      "source_health": {
        "status": "verified"
      }
    },
    "teams": {
      "athletics": {
        "items": [
          {
            "headline": "Gelof exits in 3rd inning with right knee laceration after sliding into fence",
            "url": "https://www.mlb.com/athletics/news/zack-gelof-exits-after-sliding-into-fence-vs-tigers",
            "source": "MLB.com",
            "source_type": "rss",
            "published_at": "2026-07-10T02:24:00Z",
            "summary": ""
          },
          {
            "headline": "Kurtz the 3rd sidelined as stomach bug moves through A's clubhouse",
            "url": "https://www.mlb.com/athletics/news/nick-kurtz-illness-against-tigers",
            "source": "MLB.com",
            "source_type": "rss",
            "published_at": "2026-07-09T03:23:00Z",
            "summary": ""
          },
          {
            "headline": "Price drop! Stream games on ATHLETICS.TV",
            "url": "https://www.mlb.com/athletics/news/athletics-tv-stream-2026",
            "source": "MLB.com",
            "source_type": "rss",
            "published_at": "2026-07-01T16:02:00Z",
            "summary": ""
          },
          {
            "headline": "Here's why Muncy is the odd man out as Soderstrom returns",
            "url": "https://www.mlb.com/athletics/news/tyler-soderstrom-returns-from-injury-max-muncy-optioned",
            "source": "MLB.com",
            "source_type": "rss",
            "published_at": "2026-07-08T23:01:56Z",
            "summary": ""
          },
          {
            "headline": "After capitalizing on recent picks, A's eager to pick 8th overall in Draft",
            "url": "https://www.mlb.com/athletics/news/a-s-2026-draft-preview",
            "source": "MLB.com",
            "source_type": "rss",
            "published_at": "2026-07-08T16:09:37Z",
            "summary": ""
          },
          {
            "headline": "Watch LIVE as 'Tommy Tanks' looks to slug at Triple-A",
            "url": "https://www.mlb.com/athletics/news/watch-minor-league-baseball-games-for-free-2026",
            "source": "MLB.com",
            "source_type": "rss",
            "published_at": "2026-07-10T01:58:00Z",
            "summary": ""
          },
          {
            "headline": "Here is a look at each club's best Draft pick from the past 10 years",
            "url": "https://www.mlb.com/athletics/news/best-mlb-draft-picks-of-the-past-10-years",
            "source": "MLB.com",
            "source_type": "rss",
            "published_at": "2026-07-10T01:12:00Z",
            "summary": ""
          },
          {
            "headline": "Latest Athletics injuries and transactions",
            "url": "https://www.mlb.com/athletics/news/athletics-injuries-and-roster-moves",
            "source": "MLB.com",
            "source_type": "rss",
            "published_at": "2026-07-10T02:14:00Z",
            "summary": ""
          },
          {
            "headline": "A's Top 30 Prospects list",
            "url": "https://www.mlb.com/milb/prospects/2026/athletics/",
            "source": "MLB.com",
            "source_type": "rss",
            "published_at": "2024-03-06T19:00:00Z",
            "summary": "Who do the Athletics have in the pipeline? Get scouting reports, video, stats, projected ETAs and more for the A's Top 30 Prospects."
          },
          {
            "headline": "Can getting healthy jump-start the A's for strong second half?",
            "url": "https://www.mlb.com/athletics/news/athletics-returning-key-players-2026",
            "source": "MLB.com",
            "source_type": "rss",
            "published_at": "2026-07-08T02:55:00Z",
            "summary": ""
          }
        ],
        "source_health": {
          "status": "verified"
        }
      },
      "tigers": {
        "items": [
          {
            "headline": "Valencia makes dream debut, becomes 10th Tiger to homer in first MLB at-bat",
            "url": "https://www.mlb.com/tigers/news/eduardo-valencia-homers-in-first-mlb-at-bat",
            "source": "MLB.com",
            "source_type": "rss",
            "published_at": "2026-07-10T03:25:00Z",
            "summary": ""
          },
          {
            "headline": "Melton (9 K's) learning from a master, one move at a time",
            "url": "https://www.mlb.com/tigers/news/troy-melton-strikes-out-career-high-9-against-athletics",
            "source": "MLB.com",
            "source_type": "rss",
            "published_at": "2026-07-09T03:59:00Z",
            "summary": ""
          },
          {
            "headline": "Stream Tigers games on Detroit SportsNet",
            "url": "https://www.mlb.com/tigers/news/detroit-sportsnet-launches",
            "source": "MLB.com",
            "source_type": "rss",
            "published_at": "2026-03-26T14:14:00Z",
            "summary": ""
          },
          {
            "headline": "Verlander, named All-Star Legend Pick, will retire after this season",
            "url": "https://www.mlb.com/tigers/news/justin-verlander-legacy-all-star",
            "source": "MLB.com",
            "source_type": "rss",
            "published_at": "2026-07-08T21:56:00Z",
            "summary": ""
          },
          {
            "headline": "X-rays negative on Dingler's right hand; Valencia called up for depth behind Rogers",
            "url": "https://www.mlb.com/tigers/news/dillon-dingler-exits-early-after-foul-tip-to-hand",
            "source": "MLB.com",
            "source_type": "rss",
            "published_at": "2026-07-09T20:38:00Z",
            "summary": ""
          },
          {
            "headline": "'I drink a lot of milk': Tigers' No. 2 prospect bulks up with career-high 5-hit, 6-RBI game",
            "url": "https://www.mlb.com/tigers/news/tigers-bryce-rainer-tallies-career-high-five-hits-six-rbi",
            "source": "MLB.com",
            "source_type": "rss",
            "published_at": "2026-07-09T03:18:00Z",
            "summary": ""
          },
          {
            "headline": "All-Stars show why the Draft is crucial to Tigers' success",
            "url": "https://www.mlb.com/tigers/news/tigers-2026-draft-preview",
            "source": "MLB.com",
            "source_type": "rss",
            "published_at": "2026-07-07T20:04:02Z",
            "summary": ""
          },
          {
            "headline": "Latest Tigers injuries and transactions",
            "url": "https://www.mlb.com/tigers/news/tigers-injuries-and-roster-moves",
            "source": "MLB.com",
            "source_type": "rss",
            "published_at": "2026-07-09T21:08:00Z",
            "summary": ""
          },
          {
            "headline": "Tigers' Top 30 Prospects list",
            "url": "https://www.mlb.com/milb/prospects/2026/tigers/",
            "source": "MLB.com",
            "source_type": "rss",
            "published_at": "2024-03-06T00:00:00Z",
            "summary": "Who do the Tigers have in the pipeline? Get scouting reports, video, stats, projected ETAs and more for Detroit's Top 30 Prospects."
          },
          {
            "headline": "Here is a look at each club's best Draft pick from the past 10 years",
            "url": "https://www.mlb.com/tigers/news/best-mlb-draft-picks-of-the-past-10-years",
            "source": "MLB.com",
            "source_type": "rss",
            "published_at": "2026-07-10T01:12:00Z",
            "summary": ""
          }
        ],
        "source_health": {
          "status": "verified"
        }
      },
      "rockies": {
        "items": [
          {
            "headline": "Rockies-Giants highlights",
            "url": "https://www.mlb.com/stories/game/823201",
            "source": "MLB.com",
            "source_type": "rss",
            "published_at": "2026-07-10T04:44:54Z",
            "summary": ""
          },
          {
            "headline": "'Elite' fastball, Brad Pitt's 'F1' POV power Hughes to gem in LA",
            "url": "https://www.mlb.com/rockies/news/gabriel-hughes-shines-in-first-mlb-start-at-dodger-stadium",
            "source": "MLB.com",
            "source_type": "rss",
            "published_at": "2026-07-09T07:12:14Z",
            "summary": "Rockies' No. 16 prospect overcomes tough opening to log quality start vs. Dodgers"
          },
          {
            "headline": "All-Star Sale -- Get ROCKIES.TV for $27.99",
            "url": "https://www.mlb.com/rockies/news/rockies-tv-all-star-sale-for-july-2026",
            "source": "MLB.com",
            "source_type": "rss",
            "published_at": "2026-07-06T16:22:14Z",
            "summary": ""
          },
          {
            "headline": "Rockies looking to find 1st-round success with No. 10 overall pick",
            "url": "https://www.mlb.com/rockies/news/rockies-2026-draft-preview",
            "source": "MLB.com",
            "source_type": "rss",
            "published_at": "2026-07-07T23:26:32Z",
            "summary": ""
          },
          {
            "headline": "Goodman still interested in Derby if invited -- and if hand improves",
            "url": "https://www.mlb.com/rockies/news/hunter-goodman-scratched-from-rockies-lineup-with-hand-injury",
            "source": "MLB.com",
            "source_type": "rss",
            "published_at": "2026-07-09T07:18:00Z",
            "summary": ""
          },
          {
            "headline": "Here is a look at each club's best Draft pick from the past 10 years",
            "url": "https://www.mlb.com/rockies/news/best-mlb-draft-picks-of-the-past-10-years",
            "source": "MLB.com",
            "source_type": "rss",
            "published_at": "2026-07-10T01:12:00Z",
            "summary": ""
          },
          {
            "headline": "Rockies' bullpen locks down Dodgers with help from savvy backup catcher",
            "url": "https://www.mlb.com/rockies/news/juan-mejia-jordan-romano-shut-down-dodgers-in-rockies-comeback-win",
            "source": "MLB.com",
            "source_type": "rss",
            "published_at": "2026-07-08T07:11:00Z",
            "summary": ""
          },
          {
            "headline": "Latest Rockies injuries & transactions",
            "url": "https://www.mlb.com/rockies/news/rockies-injuries-and-roster-moves",
            "source": "MLB.com",
            "source_type": "rss",
            "published_at": "2026-07-10T02:13:00Z",
            "summary": ""
          },
          {
            "headline": "Rockies' Top 30 Prospects list",
            "url": "https://www.mlb.com/milb/prospects/2026/rockies/",
            "source": "MLB.com",
            "source_type": "rss",
            "published_at": "2024-03-07T02:00:00Z",
            "summary": "Who do the Rockies have in the pipeline? Get scouting reports, video, stats, projected ETAs and more for Colorado's Top 30 Prospects."
          },
          {
            "headline": "Rumfield gets first-place votes in latest ROY poll",
            "url": "https://www.mlb.com/rockies/news/rookie-of-the-year-poll-july-2026",
            "source": "MLB.com",
            "source_type": "rss",
            "published_at": "2026-07-08T18:05:00Z",
            "summary": ""
          }
        ],
        "source_health": {
          "status": "verified"
        }
      }
    },
    "news_items": [
      {
        "id": "mlb_com-1-4",
        "headline": "Langford's early return saves Rangers with walk-off winner",
        "url": "https://www.mlb.com/news/wyatt-langford-activated-off-injured-list-after-left-hamstring-strain",
        "source": "MLB.com",
        "source_type": "rss",
        "published_at": "2026-07-10T04:39:00Z",
        "summary": "",
        "teams": [
          "rangers"
        ],
        "players": [],
        "topics": [
          "mlb"
        ],
        "priority": 1
      },
      {
        "id": "mlb_com-1-1",
        "headline": "Bauers pulls something out of 'The Matrix' to kickstart Brewers' rally",
        "url": "https://www.mlb.com/news/jake-bauers-pulls-off-impressive-dive-to-avoid-tag",
        "source": "MLB.com",
        "source_type": "rss",
        "published_at": "2026-07-10T04:36:00Z",
        "summary": "",
        "teams": [
          "brewers"
        ],
        "players": [],
        "topics": [
          "mlb"
        ],
        "priority": 1
      },
      {
        "id": "mlb_com-1-3",
        "headline": "12 starting pitchers who could be on the move before the Trade Deadline",
        "url": "https://www.mlb.com/news/starting-pitcher-trade-rumors-2026-trade-deadline",
        "source": "MLB.com",
        "source_type": "rss",
        "published_at": "2026-07-10T04:00:18Z",
        "summary": "",
        "teams": [],
        "players": [],
        "topics": [
          "mlb"
        ],
        "priority": 1
      },
      {
        "id": "mlb_com-1-7",
        "headline": "The 'first All-Star Game' had long throw contests and actors lassoing players",
        "url": "https://www.mlb.com/news/1917-all-star-game-longest-throw-fungo-contest",
        "source": "MLB.com",
        "source_type": "rss",
        "published_at": "2026-07-10T04:00:15Z",
        "summary": "",
        "teams": [
          "athletics"
        ],
        "players": [],
        "topics": [
          "mlb"
        ],
        "priority": 1
      },
      {
        "id": "yahoo_sports-3-1",
        "headline": "Cubs Minor League Wrap: Iowa routs the Saints, 21-7",
        "url": "https://sports.yahoo.com/articles/cubs-minor-league-wrap-iowa-035158782.html",
        "source": "SB Nation",
        "source_type": "rss",
        "published_at": "2026-07-10T03:51:58Z",
        "summary": "Iowa puts up 3 TDs on the Saints. South Bend also wins big.",
        "teams": [
          "cubs"
        ],
        "players": [],
        "topics": [
          "mlb"
        ],
        "priority": 2
      },
      {
        "id": "mlb_com-1-2",
        "headline": "Valencia makes dream debut, becomes 10th Tiger to homer in first MLB at-bat",
        "url": "https://www.mlb.com/news/eduardo-valencia-homers-in-first-mlb-at-bat",
        "source": "MLB.com",
        "source_type": "rss",
        "published_at": "2026-07-10T03:25:00Z",
        "summary": "",
        "teams": [],
        "players": [],
        "topics": [
          "mlb"
        ],
        "priority": 1
      },
      {
        "id": "yahoo_sports-3-2",
        "headline": "Bauers powers Brewers to 8-4 series finale win over Cardinals",
        "url": "https://sports.yahoo.com/articles/bauers-powers-brewers-8-4-031657517.html",
        "source": "SB Nation",
        "source_type": "rss",
        "published_at": "2026-07-10T03:16:57Z",
        "summary": "Henderson dominates in return, Bauers, Turang homer in series finale win",
        "teams": [
          "brewers",
          "cardinals"
        ],
        "players": [],
        "topics": [
          "mlb"
        ],
        "priority": 2
      },
      {
        "id": "yahoo_sports-3-3",
        "headline": "Mariners pay for their mistakes, get swept in Miami",
        "url": "https://sports.yahoo.com/articles/mariners-pay-mistakes-swept-miami-030542695.html",
        "source": "SB Nation",
        "source_type": "rss",
        "published_at": "2026-07-10T03:05:42Z",
        "summary": "Miscues and missed opportunities pile up as Mariners fall to .500 once again",
        "teams": [
          "athletics",
          "mariners",
          "marlins"
        ],
        "players": [],
        "topics": [
          "mlb"
        ],
        "priority": 2
      },
      {
        "id": "mlb_com-1-8",
        "headline": "Luzardo struts stuff as newly minted All-Star with 7 scoreless in Cincy",
        "url": "https://www.mlb.com/news/jesus-luzardo-tosses-7-scoreless-innings-in-win-after-named-2026-all-star",
        "source": "MLB.com",
        "source_type": "rss",
        "published_at": "2026-07-10T02:53:00Z",
        "summary": "",
        "teams": [
          "athletics"
        ],
        "players": [],
        "topics": [
          "mlb"
        ],
        "priority": 1
      },
      {
        "id": "yahoo_sports-3-4",
        "headline": "Jordan Walker\u2019s Homer Not Enough to Help Cardinals Beat Brewers Thursday",
        "url": "https://sports.yahoo.com/articles/jordan-walker-homer-not-enough-023815923.html",
        "source": "SB Nation",
        "source_type": "rss",
        "published_at": "2026-07-10T02:38:15Z",
        "summary": "The St. Louis Cardinals played the final game of their 5 games in 4 days marathon against Milwaukee Thursday night and many of us are happy to see the Brewers leave town. Jordan Walker would homer, but that wouldn\u2019t be enough for the Cardinals to avoid losing 4 of 5 from the Brew Crew. There [\u2026]",
        "teams": [
          "brewers",
          "cardinals"
        ],
        "players": [],
        "topics": [
          "mlb"
        ],
        "priority": 2
      },
      {
        "id": "yahoo_sports-3-5",
        "headline": "Giants ace Logan Webb deletes X account after bitter exchanges with reporter, fans",
        "url": "https://sports.yahoo.com/mlb/article/giants-ace-logan-webb-deletes-x-account-after-bitter-exchanges-with-reporter-fans-022701607.html",
        "source": "Yahoo Sports",
        "source_type": "rss",
        "published_at": "2026-07-10T02:27:01Z",
        "summary": "Webb allowed 5 runs in the first inning of Wednesday&#39;s loss to the Blue Jays \u2014 and then didn&#39;t take kindly to criticism afterwards.",
        "teams": [
          "blue jays",
          "giants"
        ],
        "players": [],
        "topics": [
          "mlb"
        ],
        "priority": 2
      },
      {
        "id": "yahoo_sports-3-6",
        "headline": "I Singer The Body Electric: Phillies 1, Reds 0",
        "url": "https://sports.yahoo.com/articles/singer-body-electric-phillies-1-013618819.html",
        "source": "SB Nation",
        "source_type": "rss",
        "published_at": "2026-07-10T01:36:18Z",
        "summary": "The Queen City saw two kingly pitching performances.",
        "teams": [
          "phillies",
          "reds"
        ],
        "players": [],
        "topics": [
          "mlb"
        ],
        "priority": 2
      },
      {
        "id": "yahoo_sports-3-7",
        "headline": "Dingers from unlikely sources power Tigers to sweep of A\u2019s",
        "url": "https://sports.yahoo.com/articles/dingers-unlikely-sources-power-tigers-012636393.html",
        "source": "SB Nation",
        "source_type": "rss",
        "published_at": "2026-07-10T01:26:36Z",
        "summary": "Framber Valdez kept the good starting pitching streak going, too.",
        "teams": [
          "tigers"
        ],
        "players": [],
        "topics": [
          "mlb"
        ],
        "priority": 2
      },
      {
        "id": "yahoo_sports-3-8",
        "headline": "A\u2019s Fall Again, Fall To Tigers 4-1",
        "url": "https://sports.yahoo.com/articles/fall-again-fall-tigers-4-012144118.html",
        "source": "SB Nation",
        "source_type": "rss",
        "published_at": "2026-07-10T01:21:44Z",
        "summary": "Another tough loss. When will it end?",
        "teams": [
          "tigers"
        ],
        "players": [],
        "topics": [
          "mlb"
        ],
        "priority": 2
      },
      {
        "id": "mlb_com-1-5",
        "headline": "6 Draft storylines to follow this weekend",
        "url": "https://www.mlb.com/news/6-mlb-draft-storylines-to-follow-2026",
        "source": "MLB.com",
        "source_type": "rss",
        "published_at": "2026-07-10T00:04:00Z",
        "summary": "",
        "teams": [],
        "players": [],
        "topics": [
          "mlb"
        ],
        "priority": 1
      },
      {
        "id": "mlb_com-1-6",
        "headline": "Trade rumors: Braves, Mason Miller, Rays-Yanks bidding war?",
        "url": "https://www.mlb.com/news/mlb-trade-rumors-and-2026-trade-deadline-news-july-9",
        "source": "MLB.com",
        "source_type": "rss",
        "published_at": "2026-07-09T19:07:00Z",
        "summary": "",
        "teams": [
          "athletics",
          "braves",
          "rays"
        ],
        "players": [],
        "topics": [
          "mlb"
        ],
        "priority": 1
      }
    ]
  },
  "scoreboard": {
    "games": [
      {
        "id": "823359",
        "away_team": "Atlanta Braves",
        "home_team": "Pittsburgh Pirates",
        "away_score": 10,
        "home_score": 5,
        "status": "Final",
        "status_detail": "Final",
        "inning": null,
        "inning_state": "",
        "start_time": "2026-07-09T16:35:00Z",
        "venue": "PNC Park",
        "probable_pitchers": {
          "away": "Bryce Elder",
          "home": "Mitch Keller"
        },
        "broadcasts": []
      },
      {
        "id": "823606",
        "away_team": "Kansas City Royals",
        "home_team": "New York Mets",
        "away_score": 3,
        "home_score": 7,
        "status": "Final",
        "status_detail": "Final",
        "inning": null,
        "inning_state": "",
        "start_time": "2026-07-09T17:10:00Z",
        "venue": "Citi Field",
        "probable_pitchers": {
          "away": "Michael Wacha",
          "home": "Sean Manaea"
        },
        "broadcasts": []
      },
      {
        "id": "822954",
        "away_team": "New York Yankees",
        "home_team": "Tampa Bay Rays",
        "away_score": 12,
        "home_score": 4,
        "status": "Final",
        "status_detail": "Final",
        "inning": null,
        "inning_state": "",
        "start_time": "2026-07-09T17:10:00Z",
        "venue": "Tropicana Field",
        "probable_pitchers": {
          "away": "Paul Blackburn",
          "home": "Drew Rasmussen"
        },
        "broadcasts": []
      },
      {
        "id": "824816",
        "away_team": "Chicago Cubs",
        "home_team": "Baltimore Orioles",
        "away_score": 2,
        "home_score": 3,
        "status": "Final",
        "status_detail": "Final",
        "inning": null,
        "inning_state": "",
        "start_time": "2026-07-09T17:35:00Z",
        "venue": "Oriole Park at Camden Yards",
        "probable_pitchers": {
          "away": "David Peterson",
          "home": "Trevor Rogers"
        },
        "broadcasts": []
      },
      {
        "id": "823683",
        "away_team": "Cleveland Guardians",
        "home_team": "Minnesota Twins",
        "away_score": 5,
        "home_score": 2,
        "status": "Final",
        "status_detail": "Final",
        "inning": null,
        "inning_state": "",
        "start_time": "2026-07-09T17:40:00Z",
        "venue": "Target Field",
        "probable_pitchers": {
          "away": "Gavin Williams",
          "home": "Bailey Ober"
        },
        "broadcasts": []
      },
      {
        "id": "824577",
        "away_team": "Boston Red Sox",
        "home_team": "Chicago White Sox",
        "away_score": 2,
        "home_score": 1,
        "status": "Final",
        "status_detail": "Final",
        "inning": null,
        "inning_state": "",
        "start_time": "2026-07-09T18:10:00Z",
        "venue": "Rate Field",
        "probable_pitchers": {
          "away": "Patrick Sandoval",
          "home": "Anthony Kay"
        },
        "broadcasts": []
      },
      {
        "id": "824251",
        "away_team": "Athletics",
        "home_team": "Detroit Tigers",
        "away_score": 1,
        "home_score": 4,
        "status": "Final",
        "status_detail": "Final",
        "inning": null,
        "inning_state": "",
        "start_time": "2026-07-09T22:40:00Z",
        "venue": "Comerica Park",
        "probable_pitchers": {
          "away": "Jos\u00e9 Suarez",
          "home": "Framber Valdez"
        },
        "broadcasts": []
      },
      {
        "id": "823846",
        "away_team": "Seattle Mariners",
        "home_team": "Miami Marlins",
        "away_score": 4,
        "home_score": 8,
        "status": "Final",
        "status_detail": "Final",
        "inning": null,
        "inning_state": "",
        "start_time": "2026-07-09T22:40:00Z",
        "venue": "loanDepot park",
        "probable_pitchers": {
          "away": "Bryce Miller",
          "home": "Janson Junk"
        },
        "broadcasts": []
      },
      {
        "id": "824494",
        "away_team": "Philadelphia Phillies",
        "home_team": "Cincinnati Reds",
        "away_score": 1,
        "home_score": 0,
        "status": "Final",
        "status_detail": "Final",
        "inning": null,
        "inning_state": "",
        "start_time": "2026-07-09T23:10:00Z",
        "venue": "Great American Ball Park",
        "probable_pitchers": {
          "away": "Jes\u00fas Luzardo",
          "home": "Brady Singer"
        },
        "broadcasts": []
      },
      {
        "id": "823034",
        "away_team": "Milwaukee Brewers",
        "home_team": "St. Louis Cardinals",
        "away_score": 8,
        "home_score": 4,
        "status": "Final",
        "status_detail": "Final",
        "inning": null,
        "inning_state": "",
        "start_time": "2026-07-09T23:45:00Z",
        "venue": "Busch Stadium",
        "probable_pitchers": {
          "away": "Logan Henderson",
          "home": "Andre Pallante"
        },
        "broadcasts": []
      },
      {
        "id": "822877",
        "away_team": "Los Angeles Angels",
        "home_team": "Texas Rangers",
        "away_score": 6,
        "home_score": 7,
        "status": "Final",
        "status_detail": "Final",
        "inning": null,
        "inning_state": "",
        "start_time": "2026-07-10T00:05:00Z",
        "venue": "Globe Life Field",
        "probable_pitchers": {
          "away": "Reid Detmers",
          "home": "Nathan Eovaldi"
        },
        "broadcasts": []
      },
      {
        "id": "823277",
        "away_team": "Arizona Diamondbacks",
        "home_team": "San Diego Padres",
        "away_score": 3,
        "home_score": 1,
        "status": "Final",
        "status_detail": "Final",
        "inning": null,
        "inning_state": "",
        "start_time": "2026-07-10T01:40:00Z",
        "venue": "Petco Park",
        "probable_pitchers": {
          "away": "Merrill Kelly",
          "home": "Griffin Canning"
        },
        "broadcasts": []
      },
      {
        "id": "823201",
        "away_team": "Colorado Rockies",
        "home_team": "San Francisco Giants",
        "away_score": 2,
        "home_score": 8,
        "status": "Final",
        "status_detail": "Final",
        "inning": null,
        "inning_state": "",
        "start_time": "2026-07-10T01:45:00Z",
        "venue": "Oracle Park",
        "probable_pitchers": {
          "away": "Ryan Feltner",
          "home": "Carson Whisenhunt"
        },
        "broadcasts": []
      }
    ]
  },
  "news_status": {
    "league_news": "verified",
    "teams": {
      "athletics": "verified",
      "tigers": "verified",
      "rockies": "verified"
    }
  },
  "league": {
    "headline": "League snapshot from MLB Stats API.",
    "verified_notes": [
      "Standings: Rays: 54-37 (PCT .593, GB -) [Division]",
      "Standings: Yankees: 51-42 (PCT .548, GB 4.0) [Division]",
      "Standings: Blue Jays: 44-49 (PCT .473, GB 11.0) [Division]",
      "Standings: Red Sox: 43-48 (PCT .473, GB 11.0) [Division]",
      "Standings: Orioles: 43-51 (PCT .457, GB 12.5) [Division]",
      "Standings: White Sox: 47-45 (PCT .511, GB -) [Division]",
      "Standings: Guardians: 48-46 (PCT .511, GB -) [Division]",
      "Standings: Twins: 46-48 (PCT .489, GB 2.0) [Division]",
      "Probable: Atlanta Braves (Bryce Elder) @ Pittsburgh Pirates (Mitch Keller) \u2014 Final 2026-07-09T16:35:00Z PNC Park",
      "Probable: Kansas City Royals (Michael Wacha) @ New York Mets (Sean Manaea) \u2014 Final 2026-07-09T17:10:00Z Citi Field",
      "Probable: New York Yankees (Paul Blackburn) @ Tampa Bay Rays (Drew Rasmussen) \u2014 Final 2026-07-09T17:10:00Z Tropicana Field",
      "Probable: Chicago Cubs (David Peterson) @ Baltimore Orioles (Trevor Rogers) \u2014 Final 2026-07-09T17:35:00Z Oriole Park at Camden Yards",
      "Probable: Cleveland Guardians (Gavin Williams) @ Minnesota Twins (Bailey Ober) \u2014 Final 2026-07-09T17:40:00Z Target Field",
      "Probable: Boston Red Sox (Patrick Sandoval) @ Chicago White Sox (Anthony Kay) \u2014 Final 2026-07-09T18:10:00Z Rate Field"
    ],
    "unverified_notes": [],
    "stories": [
      "Use only verified league records/matchups/transactions for hard claims."
    ],
    "watch": [
      "Probable: Atlanta Braves (Bryce Elder) @ Pittsburgh Pirates (Mitch Keller) \u2014 Final 2026-07-09T16:35:00Z PNC Park",
      "Probable: Kansas City Royals (Michael Wacha) @ New York Mets (Sean Manaea) \u2014 Final 2026-07-09T17:10:00Z Citi Field",
      "Probable: New York Yankees (Paul Blackburn) @ Tampa Bay Rays (Drew Rasmussen) \u2014 Final 2026-07-09T17:10:00Z Tropicana Field",
      "Probable: Chicago Cubs (David Peterson) @ Baltimore Orioles (Trevor Rogers) \u2014 Final 2026-07-09T17:35:00Z Oriole Park at Camden Yards",
      "Probable: Cleveland Guardians (Gavin Williams) @ Minnesota Twins (Bailey Ober) \u2014 Final 2026-07-09T17:40:00Z Target Field",
      "Probable: Boston Red Sox (Patrick Sandoval) @ Chicago White Sox (Anthony Kay) \u2014 Final 2026-07-09T18:10:00Z Rate Field",
      "Probable: Athletics (Jos\u00e9 Suarez) @ Detroit Tigers (Framber Valdez) \u2014 Final 2026-07-09T22:40:00Z Comerica Park",
      "Probable: Seattle Mariners (Bryce Miller) @ Miami Marlins (Janson Junk) \u2014 Final 2026-07-09T22:40:00Z loanDepot park"
    ],
    "transactions": [
      "League tx: 2026-07-02: New York Mets sent RHP Dedniel N\u00fa\u00f1ez on a rehab assignment to Binghamton Rumble Ponies.",
      "League tx: 2026-07-02: OF Imbert Martinez assigned to Light Blue-South.",
      "League tx: 2026-07-02: OF Roalbert Carmona assigned to Light Blue-South.",
      "League tx: 2026-07-02: IF Wallys De La Cruz assigned to Green-South.",
      "League tx: 2026-07-02: RHP Aidan Anderson suspended.",
      "League tx: 2026-07-02: Wichita Wind Surge activated RHP Nick Mikolajchak from the Development List.",
      "League tx: 2026-07-02: C Sam Huff elected free agency.",
      "League tx: 2026-07-02: Texas Rangers sent LHP Jordan Montgomery on a rehab assignment to Round Rock Express.",
      "League tx: 2026-07-02: LHP Thomas Mitchell assigned to Harwich Mariners.",
      "League tx: 2026-07-02: C Zack Thompson assigned to West Virginia Black Bears.",
      "League tx: 2026-07-02: IF Edwin German assigned to Green-South.",
      "League tx: 2026-07-02: Dunedin Blue Jays activated SS Owen Gregg from the 7-day injured list.",
      "League tx: 2026-07-02: Sugar Land Space Cowboys activated C Fernando Caldera from the Development List.",
      "League tx: 2026-07-02: 3B Drey Barrett assigned to Chatham Anglers.",
      "League tx: 2026-07-02: Chesapeake Baysox activated SS Carter Young.",
      "League tx: 2026-07-02: Atlanta Braves designated 1B Rowdy Tellez for assignment.",
      "League tx: 2026-07-02: LHP Gabriel Lopez assigned to South Stars.",
      "League tx: 2026-07-02: Frederick Keys placed C Ryan Stafford on the 7-day injured list.",
      "League tx: 2026-07-02: Tacoma Rainiers activated LHP Jhonathan D\u00edaz.",
      "League tx: 2026-07-02: RHP Cade McGarrh assigned to Mahoning Valley Scrappers.",
      "League tx: 2026-07-02: RHP Luiyi Acevedo assigned to Orange-North.",
      "League tx: 2026-07-02: Dayton Dragons activated RHP Brady Afthim.",
      "League tx: 2026-07-02: Salt Lake Bees released LHP Joey Lucchesi.",
      "League tx: 2026-07-02: Scranton/Wilkes-Barre RailRiders placed RHP Carlos Lagrange on the 7-day injured list.",
      "League tx: 2026-07-02: Texas Rangers signed free agent 3B Santiago Espinal to a minor league contract.",
      "League tx: 2026-07-02: ACL Reds activated RHP Owen Pote from the 60-day injured list.",
      "League tx: 2026-07-02: FCL Phillies activated C Rey Cruz from the 60-day injured list.",
      "League tx: 2026-07-02: 3B Santiago Espinal assigned to Round Rock Express.",
      "League tx: 2026-07-02: RHP Domingo Munoz assigned to Orange-North.",
      "League tx: 2026-07-02: Reading Fightin Phils transferred RHP Luke Russo to the Development List.",
      "League tx: 2026-07-02: Lehigh Valley IronPigs placed 3B Carter Kieboom on the 7-day injured list.",
      "League tx: 2026-07-02: Bravos de Leon released RHP Junior Santos.",
      "League tx: 2026-07-02: New York Yankees activated RHP David Bednar from the paternity list.",
      "League tx: 2026-07-02: St. Paul Saints transferred C Ian Daugherty to the Development List.",
      "League tx: 2026-07-02: LHP Alex Waye assigned to Pulaski River Turtles.",
      "League tx: 2026-07-02: Scranton/Wilkes-Barre RailRiders activated RHP Rafael Montero from the temporarily inactive list.",
      "League tx: 2026-07-02: FCL Orioles transferred RHP Salvador Casado from the 7-day injured list to the 60-day injured list.",
      "League tx: 2026-07-02: Sacramento River Cats activated RHP Wilkin Ramos.",
      "League tx: 2026-07-02: Daytona Tortugas activated LHP Hunter Hollan from the 60-day injured list.",
      "League tx: 2026-07-02: Scranton/Wilkes-Barre RailRiders transferred RHP Dom Hamel to the Development List.",
      "League tx: 2026-07-02: Athletics designated LHP Matt Krook for assignment.",
      "League tx: 2026-07-02: Boston Red Sox sent 3B Nick Sogard on a rehab assignment to Portland Sea Dogs.",
      "League tx: 2026-07-02: RHP Brian Garmon II assigned to West Virginia Black Bears.",
      "League tx: 2026-07-02: Chicago Cubs signed free agent RHP Jacob Wallace to a minor league contract.",
      "League tx: 2026-07-02: OF James McCoy assigned to Williamsport Crosscutters.",
      "League tx: 2026-07-02: LHP Logan Van Treeck retired.",
      "League tx: 2026-07-02: Kansas City Royals designated RHP Eric Cerantola for assignment.",
      "League tx: 2026-07-02: Tacoma Rainiers transferred 1B Hogan Windish to the Development List.",
      "League tx: 2026-07-02: Birmingham Barons placed RHP Morris Austin on the 7-day injured list.",
      "League tx: 2026-07-02: Spokane Indians placed OF Max Belyeu on the 7-day injured list."
    ],
    "transactions_total": 1646,
    "debug": {
      "standings": [
        "rows=30"
      ],
      "schedule": [
        "games=13"
      ],
      "transactions": [
        "transactions=1667"
      ]
    }
  },
  "teams": {
    "athletics": {
      "headline": "Athletics source snapshot from MLB Stats API.",
      "emotion": "Measured",
      "verified_notes": [
        "Standings: Athletics: 41-52 (PCT .441, GB 6.0) [Division]",
        "Probable: Athletics (Jos\u00e9 Suarez) @ Detroit Tigers (Framber Valdez) \u2014 Final 2026-07-09T22:40:00Z Comerica Park",
        "Probable: Athletics (Jacob Lopez) @ Chicago White Sox (Sean Burke) \u2014 Scheduled 2026-07-10T23:40:00Z Rate Field",
        "Athletics tx: 2026-07-02: Athletics activated LHP Jos\u00e9 Suarez from the paternity list.",
        "Athletics tx: 2026-07-02: Athletics designated LHP Matt Krook for assignment.",
        "Athletics tx: 2026-07-03: Athletics activated RHP Mark Leiter Jr. from the 15-day injured list.",
        "Athletics tx: 2026-07-03: Athletics designated RHP Geoff Hartlieb for assignment."
      ],
      "unverified_notes": [],
      "notes": [
        "Editorial framing only; do not promote UNVERIFIED entries as facts."
      ],
      "checklist": [
        "Recheck sources before air.",
        "Promote only verified entries to on-air claims."
      ],
      "source_status": {
        "athletics_standings": "verified",
        "athletics_schedule": "verified",
        "athletics_transactions": "verified"
      },
      "debug": {
        "athletics_standings": [
          "rows=30"
        ],
        "athletics_schedule": [
          "games=3"
        ],
        "athletics_transactions": [
          "transactions=18"
        ]
      }
    },
    "rockies": {
      "headline": "Colorado Rockies source snapshot from MLB Stats API.",
      "emotion": "Measured",
      "verified_notes": [
        "Standings: Rockies: 38-57 (PCT .400, GB 23.5) [Division]",
        "Probable: Colorado Rockies (Ryan Feltner) @ San Francisco Giants (Carson Whisenhunt) \u2014 Final 2026-07-10T01:45:00Z Oracle Park",
        "Probable: Colorado Rockies (Tanner Gordon) @ San Francisco Giants (Robbie Ray) \u2014 Scheduled 2026-07-11T02:15:00Z Oracle Park",
        "Colorado Rockies tx: 2026-07-03: Colorado Rockies sent RHP John Brebbia outright to Albuquerque Isotopes.",
        "Colorado Rockies tx: 2026-07-04: Colorado Rockies placed RHP Tomoyuki Sugano on the 15-day injured list retroactive to July 1, 2026. Back spasms.",
        "Colorado Rockies tx: 2026-07-04: Colorado Rockies placed RHP Seth Halvorsen on the 15-day injured list retroactive to July 1, 2026. Right shoulder inflammation.",
        "Colorado Rockies tx: 2026-07-04: Colorado Rockies selected the contract of RHP Jordan Romano from Albuquerque Isotopes."
      ],
      "unverified_notes": [],
      "notes": [
        "Editorial framing only; do not promote UNVERIFIED entries as facts."
      ],
      "checklist": [
        "Recheck sources before air.",
        "Promote only verified entries to on-air claims."
      ],
      "source_status": {
        "rockies_standings": "verified",
        "rockies_schedule": "verified",
        "rockies_transactions": "verified"
      },
      "debug": {
        "rockies_standings": [
          "rows=30"
        ],
        "rockies_schedule": [
          "games=3"
        ],
        "rockies_transactions": [
          "transactions=8"
        ]
      }
    },
    "tigers": {
      "headline": "Detroit Tigers source snapshot from MLB Stats API.",
      "emotion": "Measured",
      "verified_notes": [
        "Standings: Tigers: 43-50 (PCT .462, GB 4.5) [Division]",
        "Probable: Athletics (Jos\u00e9 Suarez) @ Detroit Tigers (Framber Valdez) \u2014 Final 2026-07-09T22:40:00Z Comerica Park",
        "Probable: Philadelphia Phillies (Aaron Nola) @ Detroit Tigers (Jack Flaherty) \u2014 Scheduled 2026-07-10T22:40:00Z Comerica Park",
        "Detroit Tigers tx: 2026-07-05: Detroit Tigers traded RHP Matt Seelinger to New York Mets for cash.",
        "Detroit Tigers tx: 2026-07-05: Detroit Tigers traded RHP Matt Seelinger to New York Mets for cash.",
        "Detroit Tigers tx: 2026-07-05: Detroit Tigers traded RHP Woo-Suk Go to Minnesota Twins for cash.",
        "Detroit Tigers tx: 2026-07-05: Detroit Tigers traded RHP Woo-Suk Go to Minnesota Twins for cash."
      ],
      "unverified_notes": [],
      "notes": [
        "Editorial framing only; do not promote UNVERIFIED entries as facts."
      ],
      "checklist": [
        "Recheck sources before air.",
        "Promote only verified entries to on-air claims."
      ],
      "source_status": {
        "tigers_standings": "verified",
        "tigers_schedule": "verified",
        "tigers_transactions": "verified"
      },
      "debug": {
        "tigers_standings": [
          "rows=30"
        ],
        "tigers_schedule": [
          "games=3"
        ],
        "tigers_transactions": [
          "transactions=8"
        ]
      }
    }
  },
  "debug": {
    "source_health": {
      "league_standings": {
        "url": "https://statsapi.mlb.com/api/v1/standings?leagueId=103,104&season=2026",
        "status": "verified",
        "debug": [
          "rows=30"
        ],
        "verified_count": 30,
        "unverified_count": 0,
        "verified_sample": [
          "Standings: Rays: 54-37 (PCT .593, GB -) [Division]",
          "Standings: Yankees: 51-42 (PCT .548, GB 4.0) [Division]",
          "Standings: Blue Jays: 44-49 (PCT .473, GB 11.0) [Division]",
          "Standings: Red Sox: 43-48 (PCT .473, GB 11.0) [Division]",
          "Standings: Orioles: 43-51 (PCT .457, GB 12.5) [Division]"
        ],
        "unverified_sample": []
      },
      "league_schedule": {
        "url": "https://statsapi.mlb.com/api/v1/schedule?sportId=1&date=2026-07-09&hydrate=probablePitcher,team",
        "status": "verified",
        "debug": [
          "games=13"
        ],
        "verified_count": 13,
        "unverified_count": 0,
        "verified_sample": [
          "Probable: Atlanta Braves (Bryce Elder) @ Pittsburgh Pirates (Mitch Keller) \u2014 Final 2026-07-09T16:35:00Z PNC Park",
          "Probable: Kansas City Royals (Michael Wacha) @ New York Mets (Sean Manaea) \u2014 Final 2026-07-09T17:10:00Z Citi Field",
          "Probable: New York Yankees (Paul Blackburn) @ Tampa Bay Rays (Drew Rasmussen) \u2014 Final 2026-07-09T17:10:00Z Tropicana Field",
          "Probable: Chicago Cubs (David Peterson) @ Baltimore Orioles (Trevor Rogers) \u2014 Final 2026-07-09T17:35:00Z Oriole Park at Camden Yards",
          "Probable: Cleveland Guardians (Gavin Williams) @ Minnesota Twins (Bailey Ober) \u2014 Final 2026-07-09T17:40:00Z Target Field"
        ],
        "unverified_sample": []
      },
      "league_transactions": {
        "url": "https://statsapi.mlb.com/api/v1/transactions?startDate=2026-07-02&endDate=2026-07-09",
        "status": "verified",
        "debug": [
          "transactions=1667"
        ],
        "verified_count": 1646,
        "unverified_count": 0,
        "verified_sample": [
          "League tx: 2026-07-02: New York Mets sent RHP Dedniel N\u00fa\u00f1ez on a rehab assignment to Binghamton Rumble Ponies.",
          "League tx: 2026-07-02: OF Imbert Martinez assigned to Light Blue-South.",
          "League tx: 2026-07-02: OF Roalbert Carmona assigned to Light Blue-South.",
          "League tx: 2026-07-02: IF Wallys De La Cruz assigned to Green-South.",
          "League tx: 2026-07-02: RHP Aidan Anderson suspended."
        ],
        "unverified_sample": []
      },
      "athletics_standings": {
        "url": "https://statsapi.mlb.com/api/v1/standings?leagueId=103,104&season=2026",
        "status": "verified",
        "debug": [
          "rows=30"
        ],
        "verified_count": 1,
        "unverified_count": 0,
        "verified_sample": [
          "Standings: Athletics: 41-52 (PCT .441, GB 6.0) [Division]"
        ],
        "unverified_sample": []
      },
      "athletics_schedule": {
        "url": "https://statsapi.mlb.com/api/v1/schedule?sportId=1&teamId=133&startDate=2026-07-09&endDate=2026-07-11&hydrate=probablePitcher,team",
        "status": "verified",
        "debug": [
          "games=3"
        ],
        "verified_count": 3,
        "unverified_count": 0,
        "verified_sample": [
          "Probable: Athletics (Jos\u00e9 Suarez) @ Detroit Tigers (Framber Valdez) \u2014 Final 2026-07-09T22:40:00Z Comerica Park",
          "Probable: Athletics (Jacob Lopez) @ Chicago White Sox (Sean Burke) \u2014 Scheduled 2026-07-10T23:40:00Z Rate Field",
          "Probable: Athletics (Gage Jump) @ Chicago White Sox (Erick Fedde) \u2014 Scheduled 2026-07-11T18:10:00Z Rate Field"
        ],
        "unverified_sample": []
      },
      "athletics_transactions": {
        "url": "https://statsapi.mlb.com/api/v1/transactions?teamId=133&startDate=2026-07-02&endDate=2026-07-09",
        "status": "verified",
        "debug": [
          "transactions=18"
        ],
        "verified_count": 18,
        "unverified_count": 0,
        "verified_sample": [
          "Athletics tx: 2026-07-02: Athletics activated LHP Jos\u00e9 Suarez from the paternity list.",
          "Athletics tx: 2026-07-02: Athletics designated LHP Matt Krook for assignment.",
          "Athletics tx: 2026-07-03: Athletics activated RHP Mark Leiter Jr. from the 15-day injured list.",
          "Athletics tx: 2026-07-03: Athletics designated RHP Geoff Hartlieb for assignment.",
          "Athletics tx: 2026-07-04: Athletics activated 3B Zack Gelof from the 10-day injured list."
        ],
        "unverified_sample": []
      },
      "rockies_standings": {
        "url": "https://statsapi.mlb.com/api/v1/standings?leagueId=103,104&season=2026",
        "status": "verified",
        "debug": [
          "rows=30"
        ],
        "verified_count": 1,
        "unverified_count": 0,
        "verified_sample": [
          "Standings: Rockies: 38-57 (PCT .400, GB 23.5) [Division]"
        ],
        "unverified_sample": []
      },
      "rockies_schedule": {
        "url": "https://statsapi.mlb.com/api/v1/schedule?sportId=1&teamId=115&startDate=2026-07-09&endDate=2026-07-11&hydrate=probablePitcher,team",
        "status": "verified",
        "debug": [
          "games=3"
        ],
        "verified_count": 3,
        "unverified_count": 0,
        "verified_sample": [
          "Probable: Colorado Rockies (Ryan Feltner) @ San Francisco Giants (Carson Whisenhunt) \u2014 Final 2026-07-10T01:45:00Z Oracle Park",
          "Probable: Colorado Rockies (Tanner Gordon) @ San Francisco Giants (Robbie Ray) \u2014 Scheduled 2026-07-11T02:15:00Z Oracle Park",
          "Probable: Colorado Rockies (Kyle Freeland) @ San Francisco Giants (Tyler Mahle) \u2014 Scheduled 2026-07-11T20:05:00Z Oracle Park"
        ],
        "unverified_sample": []
      },
      "rockies_transactions": {
        "url": "https://statsapi.mlb.com/api/v1/transactions?teamId=115&startDate=2026-07-02&endDate=2026-07-09",
        "status": "verified",
        "debug": [
          "transactions=8"
        ],
        "verified_count": 8,
        "unverified_count": 0,
        "verified_sample": [
          "Colorado Rockies tx: 2026-07-03: Colorado Rockies sent RHP John Brebbia outright to Albuquerque Isotopes.",
          "Colorado Rockies tx: 2026-07-04: Colorado Rockies placed RHP Tomoyuki Sugano on the 15-day injured list retroactive to July 1, 2026. Back spasms.",
          "Colorado Rockies tx: 2026-07-04: Colorado Rockies placed RHP Seth Halvorsen on the 15-day injured list retroactive to July 1, 2026. Right shoulder inflammation.",
          "Colorado Rockies tx: 2026-07-04: Colorado Rockies selected the contract of RHP Jordan Romano from Albuquerque Isotopes.",
          "Colorado Rockies tx: 2026-07-04: Colorado Rockies recalled LHP Sean Sullivan from Albuquerque Isotopes."
        ],
        "unverified_sample": []
      },
      "tigers_standings": {
        "url": "https://statsapi.mlb.com/api/v1/standings?leagueId=103,104&season=2026",
        "status": "verified",
        "debug": [
          "rows=30"
        ],
        "verified_count": 1,
        "unverified_count": 0,
        "verified_sample": [
          "Standings: Tigers: 43-50 (PCT .462, GB 4.5) [Division]"
        ],
        "unverified_sample": []
      },
      "tigers_schedule": {
        "url": "https://statsapi.mlb.com/api/v1/schedule?sportId=1&teamId=116&startDate=2026-07-09&endDate=2026-07-11&hydrate=probablePitcher,team",
        "status": "verified",
        "debug": [
          "games=3"
        ],
        "verified_count": 3,
        "unverified_count": 0,
        "verified_sample": [
          "Probable: Athletics (Jos\u00e9 Suarez) @ Detroit Tigers (Framber Valdez) \u2014 Final 2026-07-09T22:40:00Z Comerica Park",
          "Probable: Philadelphia Phillies (Aaron Nola) @ Detroit Tigers (Jack Flaherty) \u2014 Scheduled 2026-07-10T22:40:00Z Comerica Park",
          "Probable: Philadelphia Phillies (Cristopher S\u00e1nchez) @ Detroit Tigers (Casey Mize) \u2014 Scheduled 2026-07-11T22:10:00Z Comerica Park"
        ],
        "unverified_sample": []
      },
      "tigers_transactions": {
        "url": "https://statsapi.mlb.com/api/v1/transactions?teamId=116&startDate=2026-07-02&endDate=2026-07-09",
        "status": "verified",
        "debug": [
          "transactions=8"
        ],
        "verified_count": 8,
        "unverified_count": 0,
        "verified_sample": [
          "Detroit Tigers tx: 2026-07-05: Detroit Tigers traded RHP Matt Seelinger to New York Mets for cash.",
          "Detroit Tigers tx: 2026-07-05: Detroit Tigers traded RHP Matt Seelinger to New York Mets for cash.",
          "Detroit Tigers tx: 2026-07-05: Detroit Tigers traded RHP Woo-Suk Go to Minnesota Twins for cash.",
          "Detroit Tigers tx: 2026-07-05: Detroit Tigers traded RHP Woo-Suk Go to Minnesota Twins for cash.",
          "Detroit Tigers tx: 2026-07-06: Detroit Tigers signed free agent OF Raylin Castillo to a minor league contract."
        ],
        "unverified_sample": []
      },
      "league_news": {
        "url": "https://www.mlb.com/feeds/news/rss.xml",
        "status": "verified",
        "debug": [
          "items=10"
        ],
        "verified_count": 1,
        "unverified_count": 0,
        "verified_sample": [
          "News items: 10"
        ],
        "unverified_sample": []
      },
      "athletics_news": {
        "url": "https://www.mlb.com/athletics/feeds/news/rss.xml",
        "status": "verified",
        "debug": [
          "items=10"
        ],
        "verified_count": 1,
        "unverified_count": 0,
        "verified_sample": [
          "News items: 10"
        ],
        "unverified_sample": []
      },
      "tigers_news": {
        "url": "https://www.mlb.com/tigers/feeds/news/rss.xml",
        "status": "verified",
        "debug": [
          "items=10"
        ],
        "verified_count": 1,
        "unverified_count": 0,
        "verified_sample": [
          "News items: 10"
        ],
        "unverified_sample": []
      },
      "rockies_news": {
        "url": "https://www.mlb.com/rockies/feeds/news/rss.xml",
        "status": "verified",
        "debug": [
          "items=10"
        ],
        "verified_count": 1,
        "unverified_count": 0,
        "verified_sample": [
          "News items: 10"
        ],
        "unverified_sample": []
      },
      "curated_news_mlb_com": {
        "url": "https://www.mlb.com/feeds/news/rss.xml",
        "status": "verified",
        "debug": [
          "items=8"
        ],
        "verified_count": 1,
        "unverified_count": 0,
        "verified_sample": [
          "News items: 8"
        ],
        "unverified_sample": []
      },
      "curated_news_espn": {
        "url": "https://www.espn.com/espn/rss/mlb/news",
        "status": "unverified",
        "debug": [
          "empty_response"
        ],
        "verified_count": 0,
        "unverified_count": 1,
        "verified_sample": [],
        "unverified_sample": [
          "UNVERIFIED: News feed response was empty."
        ]
      },
      "curated_news_yahoo_sports": {
        "url": "https://sports.yahoo.com/mlb/rss.xml",
        "status": "verified",
        "debug": [
          "items=8"
        ],
        "verified_count": 1,
        "unverified_count": 0,
        "verified_sample": [
          "News items: 8"
        ],
        "unverified_sample": []
      },
      "bd_bets": {
        "url": "https://burnin-daylight-betting-production.up.railway.app/api/exports/bd-baseball/mlb?token=Zs7MjA--I8Tivn9-rPr5-OLIhk0zxyKNRTrQykrGRpA",
        "status": "unverified",
        "debug": [
          "picks=0"
        ],
        "verified_count": 0,
        "unverified_count": 0,
        "verified_sample": [],
        "unverified_sample": []
      }
    },
    "generated_utc": "2026-07-10T05:00:41Z"
  },
  "bd_bets": {
    "generated_at": "2026-07-10T05:00:43.227Z",
    "slate_date": "2026-07-10",
    "sport": "MLB",
    "source": "bd-bets",
    "picks": [],
    "insights": [],
    "source_status": "unverified",
    "feed_url": "https://burnin-daylight-betting-production.up.railway.app/api/exports/bd-baseball/mlb?token=Zs7MjA--I8Tivn9-rPr5-OLIhk0zxyKNRTrQykrGRpA"
  }
}